crab/__init__.py
crab/actions/android_actions.py
crab/actions/crab_actions.py
crab/actions/desktop_actions.py
crab/actions/file_actions.py
crab/actions/system_actions.py
crab/agents/backend_models/__init__.py
crab/agents/backend_models/claude_model.py
crab/agents/backend_models/gemini_model.py
crab/agents/backend_models/openai_model.py
crab/agents/policies/__init__.py
crab/agents/policies/multi_agent_by_env.py
crab/agents/policies/multi_agent_by_func.py
crab/agents/policies/single_agent.py
crab/benchmarks/__init__.py
crab/benchmarks/template.py
crab/core/__init__.py
crab/core/agent_policy.py
crab/core/backend_model.py
crab/core/benchmark.py
crab/core/csv_log.py
crab/core/decorators.py
crab/core/environment.py
crab/core/exceptions.py
crab/core/experiment.py
crab/core/graph_evaluator.py
crab/core/models/__init__.py
crab/core/models/action.py
crab/core/models/agent_interface.py
crab/core/models/benchmark_interface.py
crab/core/models/config.py
crab/core/models/evaluator.py
crab/core/models/task.py
crab/core/task_generator.py
crab/environments/__init__.py
crab/environments/template.py
crab/server/__init__.py
crab/server/api.py
crab/server/config.py
crab/server/exception_handlers.py
crab/server/logger.py
crab/server/main.py
crab/server/middleware.py
crab/server/utils.py
crab/utils/common.py
crab_framework-0.1.2.dist-info/METADATA
crab_framework-0.1.2.dist-info/WHEEL
crab_framework-0.1.2.dist-info/RECORD
