Metadata-Version: 2.1
Name: crab-framework
Version: 0.1.2
Summary: Cross-platform Agent Benchmark for Multimodal Embodied Language Model Agents.
Home-page: https://github.com/camel-ai/crab
License: Apache-2.0
Author: CAMEL-AI.org
Maintainer: Tianqi Xu
Maintainer-email: tianqi.xu@kaust.edu.sa
Requires-Python: >=3.10,<4.0
Classifier: License :: OSI Approved :: Apache Software License
Classifier: Programming Language :: Python :: 3
Classifier: Programming Language :: Python :: 3.10
Classifier: Programming Language :: Python :: 3.11
Classifier: Programming Language :: Python :: 3.12
Provides-Extra: client
Provides-Extra: server
Requires-Dist: addict (>=2.4.0,<3.0.0) ; extra == "client"
Requires-Dist: anthropic (>=0.26.0,<0.27.0) ; extra == "client"
Requires-Dist: beautifulsoup4 (>=4.12.3,<5.0.0)
Requires-Dist: dill (>=0.3.8,<0.4.0)
Requires-Dist: docstring-parser (>=0,<1)
Requires-Dist: easyocr (>=1.7.1,<2.0.0) ; extra == "client"
Requires-Dist: fastapi[all] (==0.109.1) ; extra == "server"
Requires-Dist: google-generativeai (>=0.5.2,<0.6.0) ; extra == "client"
Requires-Dist: groq (>=0.5.0,<0.6.0) ; extra == "client"
Requires-Dist: httpx ; extra == "client"
Requires-Dist: lxml (>=5.2.2,<6.0.0)
Requires-Dist: matplotlib (>=3.8.3,<4.0.0) ; extra == "client"
Requires-Dist: mss (>=9.0.1,<10.0.0)
Requires-Dist: networkx (>=3,<4)
Requires-Dist: numpy (>=1.26.4,<2.0.0) ; extra == "client"
Requires-Dist: odfpy (>=1.4.1,<2.0.0)
Requires-Dist: ollama (>=0.2.0,<0.3.0) ; extra == "client"
Requires-Dist: openai (>=1.12.0,<2.0.0) ; extra == "client"
Requires-Dist: opencv-python (>=4.9.0.80,<5.0.0.0) ; extra == "client"
Requires-Dist: pillow (>=10.2.0,<11.0.0)
Requires-Dist: plotly (>=5.20.0,<6.0.0) ; extra == "client"
Requires-Dist: psutil (>=5.9.8,<6.0.0)
Requires-Dist: pyautogui (>=0.9.3,<0.10.0)
Requires-Dist: pycocotools (>=2.0.7,<3.0.0) ; extra == "client"
Requires-Dist: pydantic (>=2.6,<3.0)
Requires-Dist: pydantic-settings (>=2,<3) ; extra == "server"
Requires-Dist: pyexcel-ods (>=0.6.0,<0.7.0)
Requires-Dist: pyperclip (>=1.8.2,<2.0.0)
Requires-Dist: python-vagrant (>=1.0.0,<2.0.0)
Requires-Dist: termcolor (>=2.4.0,<3.0.0)
Requires-Dist: timm (>=0.9.16,<0.10.0) ; extra == "client"
Requires-Dist: torch (>=2.2.1,<3.0.0) ; extra == "client"
Requires-Dist: torchvision (>=0.17.1,<0.18.0) ; extra == "client"
Requires-Dist: transformers (==4.42.4) ; extra == "client"
Requires-Dist: types-networkx (>=3.2.1.20240210,<4.0.0.0)
Requires-Dist: types-psutil (>=5.9.5.20240205,<6.0.0.0)
Requires-Dist: types-pyautogui (>=0.9.3.20240106,<0.10.0.0)
Requires-Dist: uvicorn[standard] (>=0.27.0.post1,<0.28.0) ; extra == "server"
Requires-Dist: yapf (>=0.40.2,<0.41.0) ; extra == "client"
Project-URL: Repository, https://github.com/camel-ai/crab
